HDDFeat/__init__.py
HDDFeat/discernibleScore.py
HDDFeat/fastFeatureSelectionDS.py
HDDFeat/increDiscernibleScore.py
HDDFeat/increFeaSltDSFilterSam.py
HDDFeat/increFeatureSelectionDS.py
HDDFeat/partition_fold.py
HDDFeat-0.1.1.dist-info/METADATA
HDDFeat-0.1.1.dist-info/WHEEL
HDDFeat-0.1.1.dist-info/top_level.txt
HDDFeat-0.1.1.dist-info/RECORD
